README.md
setup.cfg
setup.py
py_mgr_tkinter/__init__.py
py_mgr_tkinter/core.py
py_mgr_tkinter.egg-info/PKG-INFO
py_mgr_tkinter.egg-info/SOURCES.txt
py_mgr_tkinter.egg-info/dependency_links.txt
py_mgr_tkinter.egg-info/top_level.txt