Metadata-Version: 2.1
Name: py-mgr-tkinter
Version: 0.0.9
Summary: lib tkinter for py-mgr
Home-page: https://github.com/FlavioLionelRita/py-mgr-tkinter
Author: Flavio Lionel Rita
Author-email: flaviolrita@hotmail.com
License: UNKNOWN
Download-URL: https://github.com/FlavioLionelRita/py-mgr-tkinter/tarball/0.0.1
Keywords: manager,plugin,tkinter
Platform: UNKNOWN
